{
  "moduleName": "churchapp",
  "tables": [
    {
      "name": "chat_rooms",
      "dartName": "ChatRoom",
      "module": "churchapp",
      "schema": "public",
      "columns": [
        {
          "name": "id",
          "columnType": 2,
          "isNullable": false,
          "columnDefault": "nextval('chat_rooms_id_seq'::regclass)",
          "dartType": "int?"
        },
        {
          "name": "createdOn",
          "columnType": 4,
          "isNullable": true,
          "dartType": "DateTime?"
        },
        {
          "name": "lastMessage",
          "columnType": 0,
          "isNullable": true,
          "dartType": "String?"
        },
        {
          "name": "lastSentBy",
          "columnType": 8,
          "isNullable": true,
          "dartType": "protocol:Contact?"
        },
        {
          "name": "lastSentAt",
          "columnType": 4,
          "isNullable": true,
          "dartType": "DateTime?"
        },
        {
          "name": "createdBy",
          "columnType": 8,
          "isNullable": true,
          "dartType": "protocol:Contact?"
        },
        {
          "name": "_servicesDiscussionsServicesId",
          "columnType": 2,
          "isNullable": true,
          "dartType": "int?"
        }
      ],
      "foreignKeys": [
        {
          "constraintName": "chat_rooms_fk_0",
          "columns": [
            "_servicesDiscussionsServicesId"
          ],
          "referenceTable": "services",
          "referenceTableSchema": "public",
          "referenceColumns": [
            "id"
          ],
          "onUpdate": 3,
          "onDelete": 3
        }
      ],
      "indexes": [
        {
          "indexName": "chat_rooms_pkey",
          "elements": [
            {
              "type": 0,
              "definition": "id"
            }
          ],
          "type": "btree",
          "isUnique": true,
          "isPrimary": true
        }
      ],
      "managed": true
    },
    {
      "name": "comments",
      "dartName": "Comment",
      "module": "churchapp",
      "schema": "public",
      "columns": [
        {
          "name": "id",
          "columnType": 2,
          "isNullable": false,
          "columnDefault": "nextval('comments_id_seq'::regclass)",
          "dartType": "int?"
        },
        {
          "name": "sent",
          "columnType": 4,
          "isNullable": false,
          "dartType": "DateTime"
        },
        {
          "name": "delivered",
          "columnType": 4,
          "isNullable": true,
          "dartType": "DateTime?"
        },
        {
          "name": "received",
          "columnType": 4,
          "isNullable": true,
          "dartType": "DateTime?"
        },
        {
          "name": "read",
          "columnType": 4,
          "isNullable": true,
          "dartType": "DateTime?"
        },
        {
          "name": "text",
          "columnType": 0,
          "isNullable": true,
          "dartType": "String?"
        },
        {
          "name": "file",
          "columnType": 8,
          "isNullable": true,
          "dartType": "protocol:FileStore?"
        },
        {
          "name": "sentBy",
          "columnType": 8,
          "isNullable": true,
          "dartType": "protocol:Contact?"
        }
      ],
      "foreignKeys": [],
      "indexes": [
        {
          "indexName": "comments_pkey",
          "elements": [
            {
              "type": 0,
              "definition": "id"
            }
          ],
          "type": "btree",
          "isUnique": true,
          "isPrimary": true
        }
      ],
      "managed": true
    },
    {
      "name": "contact_type",
      "dartName": "ContactType",
      "module": "churchapp",
      "schema": "public",
      "columns": [
        {
          "name": "id",
          "columnType": 2,
          "isNullable": false,
          "columnDefault": "nextval('contact_type_id_seq'::regclass)",
          "dartType": "int?"
        },
        {
          "name": "description",
          "columnType": 0,
          "isNullable": true,
          "dartType": "String?"
        },
        {
          "name": "color",
          "columnType": 0,
          "isNullable": true,
          "dartType": "String?"
        }
      ],
      "foreignKeys": [],
      "indexes": [
        {
          "indexName": "contact_type_pkey",
          "elements": [
            {
              "type": 0,
              "definition": "id"
            }
          ],
          "type": "btree",
          "isUnique": true,
          "isPrimary": true
        }
      ],
      "managed": true
    },
    {
      "name": "contacts",
      "dartName": "Contact",
      "module": "churchapp",
      "schema": "public",
      "columns": [
        {
          "name": "id",
          "columnType": 2,
          "isNullable": false,
          "columnDefault": "nextval('contacts_id_seq'::regclass)",
          "dartType": "int?"
        },
        {
          "name": "name",
          "columnType": 0,
          "isNullable": true,
          "dartType": "String?"
        },
        {
          "name": "suffix",
          "columnType": 0,
          "isNullable": true,
          "dartType": "String?"
        },
        {
          "name": "dob",
          "columnType": 4,
          "isNullable": true,
          "dartType": "DateTime?"
        },
        {
          "name": "email",
          "columnType": 0,
          "isNullable": true,
          "dartType": "String?"
        },
        {
          "name": "address",
          "columnType": 0,
          "isNullable": true,
          "dartType": "String?"
        },
        {
          "name": "gender",
          "columnType": 0,
          "isNullable": true,
          "dartType": "protocol:Gender?"
        },
        {
          "name": "bloodGroup",
          "columnType": 0,
          "isNullable": true,
          "dartType": "protocol:BloodGroup?"
        },
        {
          "name": "emergencyContactNo",
          "columnType": 0,
          "isNullable": true,
          "dartType": "String?"
        },
        {
          "name": "mobile",
          "columnType": 0,
          "isNullable": true,
          "dartType": "String?"
        },
        {
          "name": "homePhone",
          "columnType": 0,
          "isNullable": true,
          "dartType": "String?"
        },
        {
          "name": "officePhone",
          "columnType": 0,
          "isNullable": true,
          "dartType": "String?"
        },
        {
          "name": "contactType",
          "columnType": 8,
          "isNullable": true,
          "dartType": "protocol:ContactType?"
        },
        {
          "name": "profilePic",
          "columnType": 5,
          "isNullable": true,
          "dartType": "dart:typed_data:ByteData?"
        },
        {
          "name": "_smallGroupsMembersSmallGroupsId",
          "columnType": 2,
          "isNullable": true,
          "dartType": "int?"
        },
        {
          "name": "_chatRoomsMembersChatRoomsId",
          "columnType": 2,
          "isNullable": true,
          "dartType": "int?"
        },
        {
          "name": "_sermonsAuthorsSermonsId",
          "columnType": 2,
          "isNullable": true,
          "dartType": "int?"
        },
        {
          "name": "_servicesMembersServicesId",
          "columnType": 2,
          "isNullable": true,
          "dartType": "int?"
        }
      ],
      "foreignKeys": [
        {
          "constraintName": "contacts_fk_0",
          "columns": [
            "_smallGroupsMembersSmallGroupsId"
          ],
          "referenceTable": "small_groups",
          "referenceTableSchema": "public",
          "referenceColumns": [
            "id"
          ],
          "onUpdate": 3,
          "onDelete": 3
        },
        {
          "constraintName": "contacts_fk_1",
          "columns": [
            "_chatRoomsMembersChatRoomsId"
          ],
          "referenceTable": "chat_rooms",
          "referenceTableSchema": "public",
          "referenceColumns": [
            "id"
          ],
          "onUpdate": 3,
          "onDelete": 3
        },
        {
          "constraintName": "contacts_fk_2",
          "columns": [
            "_sermonsAuthorsSermonsId"
          ],
          "referenceTable": "sermons",
          "referenceTableSchema": "public",
          "referenceColumns": [
            "id"
          ],
          "onUpdate": 3,
          "onDelete": 3
        },
        {
          "constraintName": "contacts_fk_3",
          "columns": [
            "_servicesMembersServicesId"
          ],
          "referenceTable": "services",
          "referenceTableSchema": "public",
          "referenceColumns": [
            "id"
          ],
          "onUpdate": 3,
          "onDelete": 3
        }
      ],
      "indexes": [
        {
          "indexName": "contacts_pkey",
          "elements": [
            {
              "type": 0,
              "definition": "id"
            }
          ],
          "type": "btree",
          "isUnique": true,
          "isPrimary": true
        }
      ],
      "managed": true
    },
    {
      "name": "event_group",
      "dartName": "EventGroup",
      "module": "churchapp",
      "schema": "public",
      "columns": [
        {
          "name": "id",
          "columnType": 2,
          "isNullable": false,
          "columnDefault": "nextval('event_group_id_seq'::regclass)",
          "dartType": "int?"
        },
        {
          "name": "groupId",
          "columnType": 2,
          "isNullable": false,
          "dartType": "int"
        },
        {
          "name": "eventId",
          "columnType": 2,
          "isNullable": false,
          "dartType": "int"
        },
        {
          "name": "_eventsEventgroupsEventsId",
          "columnType": 2,
          "isNullable": true,
          "dartType": "int?"
        }
      ],
      "foreignKeys": [
        {
          "constraintName": "event_group_fk_0",
          "columns": [
            "groupId"
          ],
          "referenceTable": "small_groups",
          "referenceTableSchema": "public",
          "referenceColumns": [
            "id"
          ],
          "onUpdate": 3,
          "onDelete": 3
        },
        {
          "constraintName": "event_group_fk_1",
          "columns": [
            "eventId"
          ],
          "referenceTable": "events",
          "referenceTableSchema": "public",
          "referenceColumns": [
            "id"
          ],
          "onUpdate": 3,
          "onDelete": 3
        },
        {
          "constraintName": "event_group_fk_2",
          "columns": [
            "_eventsEventgroupsEventsId"
          ],
          "referenceTable": "events",
          "referenceTableSchema": "public",
          "referenceColumns": [
            "id"
          ],
          "onUpdate": 3,
          "onDelete": 3
        }
      ],
      "indexes": [
        {
          "indexName": "event_group_pkey",
          "elements": [
            {
              "type": 0,
              "definition": "id"
            }
          ],
          "type": "btree",
          "isUnique": true,
          "isPrimary": true
        }
      ],
      "managed": true
    },
    {
      "name": "event_itenary_items",
      "dartName": "EventItenaryItem",
      "module": "churchapp",
      "schema": "public",
      "columns": [
        {
          "name": "id",
          "columnType": 2,
          "isNullable": false,
          "columnDefault": "nextval('event_itenary_items_id_seq'::regclass)",
          "dartType": "int?"
        },
        {
          "name": "title",
          "columnType": 0,
          "isNullable": true,
          "dartType": "String?"
        },
        {
          "name": "description",
          "columnType": 0,
          "isNullable": true,
          "dartType": "String?"
        },
        {
          "name": "startTime",
          "columnType": 4,
          "isNullable": true,
          "dartType": "DateTime?"
        },
        {
          "name": "duration",
          "columnType": 6,
          "isNullable": true,
          "dartType": "Duration?"
        }
      ],
      "foreignKeys": [],
      "indexes": [
        {
          "indexName": "event_itenary_items_pkey",
          "elements": [
            {
              "type": 0,
              "definition": "id"
            }
          ],
          "type": "btree",
          "isUnique": true,
          "isPrimary": true
        }
      ],
      "managed": true
    },
    {
      "name": "event_meetings",
      "dartName": "EventMeeting",
      "module": "churchapp",
      "schema": "public",
      "columns": [
        {
          "name": "id",
          "columnType": 2,
          "isNullable": false,
          "columnDefault": "nextval('event_meetings_id_seq'::regclass)",
          "dartType": "int?"
        },
        {
          "name": "title",
          "columnType": 0,
          "isNullable": true,
          "dartType": "String?"
        },
        {
          "name": "description",
          "columnType": 0,
          "isNullable": true,
          "dartType": "String?"
        },
        {
          "name": "detailedDescription",
          "columnType": 0,
          "isNullable": true,
          "dartType": "String?"
        },
        {
          "name": "meetingId",
          "columnType": 2,
          "isNullable": false,
          "dartType": "int"
        },
        {
          "name": "eventId",
          "columnType": 2,
          "isNullable": false,
          "dartType": "int"
        },
        {
          "name": "_eventsEventmeetingsEventsId",
          "columnType": 2,
          "isNullable": true,
          "dartType": "int?"
        }
      ],
      "foreignKeys": [
        {
          "constraintName": "event_meetings_fk_0",
          "columns": [
            "meetingId"
          ],
          "referenceTable": "meetings",
          "referenceTableSchema": "public",
          "referenceColumns": [
            "id"
          ],
          "onUpdate": 3,
          "onDelete": 3
        },
        {
          "constraintName": "event_meetings_fk_1",
          "columns": [
            "eventId"
          ],
          "referenceTable": "events",
          "referenceTableSchema": "public",
          "referenceColumns": [
            "id"
          ],
          "onUpdate": 3,
          "onDelete": 3
        },
        {
          "constraintName": "event_meetings_fk_2",
          "columns": [
            "_eventsEventmeetingsEventsId"
          ],
          "referenceTable": "events",
          "referenceTableSchema": "public",
          "referenceColumns": [
            "id"
          ],
          "onUpdate": 3,
          "onDelete": 3
        }
      ],
      "indexes": [
        {
          "indexName": "event_meetings_pkey",
          "elements": [
            {
              "type": 0,
              "definition": "id"
            }
          ],
          "type": "btree",
          "isUnique": true,
          "isPrimary": true
        }
      ],
      "managed": true
    },
    {
      "name": "event_types",
      "dartName": "EventType",
      "module": "churchapp",
      "schema": "public",
      "columns": [
        {
          "name": "id",
          "columnType": 2,
          "isNullable": false,
          "columnDefault": "nextval('event_types_id_seq'::regclass)",
          "dartType": "int?"
        },
        {
          "name": "description",
          "columnType": 0,
          "isNullable": true,
          "dartType": "String?"
        },
        {
          "name": "color",
          "columnType": 0,
          "isNullable": true,
          "dartType": "String?"
        },
        {
          "name": "createdBy",
          "columnType": 2,
          "isNullable": true,
          "dartType": "int?"
        },
        {
          "name": "createdAt",
          "columnType": 4,
          "isNullable": true,
          "dartType": "DateTime?"
        }
      ],
      "foreignKeys": [],
      "indexes": [
        {
          "indexName": "event_types_pkey",
          "elements": [
            {
              "type": 0,
              "definition": "id"
            }
          ],
          "type": "btree",
          "isUnique": true,
          "isPrimary": true
        }
      ],
      "managed": true
    },
    {
      "name": "events",
      "dartName": "Event",
      "module": "churchapp",
      "schema": "public",
      "columns": [
        {
          "name": "id",
          "columnType": 2,
          "isNullable": false,
          "columnDefault": "nextval('events_id_seq'::regclass)",
          "dartType": "int?"
        },
        {
          "name": "title",
          "columnType": 0,
          "isNullable": true,
          "dartType": "String?"
        },
        {
          "name": "description",
          "columnType": 0,
          "isNullable": true,
          "dartType": "String?"
        },
        {
          "name": "type",
          "columnType": 8,
          "isNullable": true,
          "dartType": "protocol:EventType?"
        }
      ],
      "foreignKeys": [],
      "indexes": [
        {
          "indexName": "events_pkey",
          "elements": [
            {
              "type": 0,
              "definition": "id"
            }
          ],
          "type": "btree",
          "isUnique": true,
          "isPrimary": true
        }
      ],
      "managed": true
    },
    {
      "name": "families",
      "dartName": "Family",
      "module": "churchapp",
      "schema": "public",
      "columns": [
        {
          "name": "id",
          "columnType": 2,
          "isNullable": false,
          "columnDefault": "nextval('families_id_seq'::regclass)",
          "dartType": "int?"
        },
        {
          "name": "familyName",
          "columnType": 0,
          "isNullable": true,
          "dartType": "String?"
        },
        {
          "name": "famMemIdx",
          "columnType": 7,
          "isNullable": false,
          "dartType": "UuidValue"
        }
      ],
      "foreignKeys": [],
      "indexes": [
        {
          "indexName": "families_pkey",
          "elements": [
            {
              "type": 0,
              "definition": "id"
            }
          ],
          "type": "btree",
          "isUnique": true,
          "isPrimary": true
        }
      ],
      "managed": true
    },
    {
      "name": "file_store",
      "dartName": "FileStore",
      "module": "churchapp",
      "schema": "public",
      "columns": [
        {
          "name": "id",
          "columnType": 2,
          "isNullable": false,
          "columnDefault": "nextval('file_store_id_seq'::regclass)",
          "dartType": "int?"
        },
        {
          "name": "title",
          "columnType": 0,
          "isNullable": true,
          "dartType": "String?"
        },
        {
          "name": "subTitle",
          "columnType": 0,
          "isNullable": true,
          "dartType": "String?"
        },
        {
          "name": "addedBy",
          "columnType": 8,
          "isNullable": true,
          "dartType": "protocol:Contact?"
        },
        {
          "name": "fileName",
          "columnType": 0,
          "isNullable": true,
          "dartType": "String?"
        },
        {
          "name": "fileType",
          "columnType": 0,
          "isNullable": true,
          "dartType": "String?"
        },
        {
          "name": "file",
          "columnType": 5,
          "isNullable": true,
          "dartType": "dart:typed_data:ByteData?"
        },
        {
          "name": "published",
          "columnType": 1,
          "isNullable": true,
          "dartType": "bool?"
        },
        {
          "name": "duration",
          "columnType": 6,
          "isNullable": true,
          "dartType": "Duration?"
        },
        {
          "name": "description",
          "columnType": 0,
          "isNullable": true,
          "dartType": "String?"
        },
        {
          "name": "fileSize",
          "columnType": 3,
          "isNullable": true,
          "dartType": "double?"
        },
        {
          "name": "_servicesFilesServicesId",
          "columnType": 2,
          "isNullable": true,
          "dartType": "int?"
        }
      ],
      "foreignKeys": [
        {
          "constraintName": "file_store_fk_0",
          "columns": [
            "_servicesFilesServicesId"
          ],
          "referenceTable": "services",
          "referenceTableSchema": "public",
          "referenceColumns": [
            "id"
          ],
          "onUpdate": 3,
          "onDelete": 3
        }
      ],
      "indexes": [
        {
          "indexName": "file_store_pkey",
          "elements": [
            {
              "type": 0,
              "definition": "id"
            }
          ],
          "type": "btree",
          "isUnique": true,
          "isPrimary": true
        }
      ],
      "managed": true
    },
    {
      "name": "group_type",
      "dartName": "GroupType",
      "module": "churchapp",
      "schema": "public",
      "columns": [
        {
          "name": "id",
          "columnType": 2,
          "isNullable": false,
          "columnDefault": "nextval('group_type_id_seq'::regclass)",
          "dartType": "int?"
        },
        {
          "name": "description",
          "columnType": 0,
          "isNullable": true,
          "dartType": "String?"
        },
        {
          "name": "color",
          "columnType": 0,
          "isNullable": true,
          "dartType": "String?"
        }
      ],
      "foreignKeys": [],
      "indexes": [
        {
          "indexName": "group_type_pkey",
          "elements": [
            {
              "type": 0,
              "definition": "id"
            }
          ],
          "type": "btree",
          "isUnique": true,
          "isPrimary": true
        }
      ],
      "managed": true
    },
    {
      "name": "meetings",
      "dartName": "Meeting",
      "module": "churchapp",
      "schema": "public",
      "columns": [
        {
          "name": "id",
          "columnType": 2,
          "isNullable": false,
          "columnDefault": "nextval('meetings_id_seq'::regclass)",
          "dartType": "int?"
        },
        {
          "name": "title",
          "columnType": 0,
          "isNullable": true,
          "dartType": "String?"
        },
        {
          "name": "description",
          "columnType": 0,
          "isNullable": true,
          "dartType": "String?"
        },
        {
          "name": "createdBy",
          "columnType": 8,
          "isNullable": true,
          "dartType": "protocol:Contact?"
        },
        {
          "name": "createdAt",
          "columnType": 4,
          "isNullable": true,
          "dartType": "DateTime?"
        },
        {
          "name": "startTime",
          "columnType": 4,
          "isNullable": true,
          "dartType": "DateTime?"
        },
        {
          "name": "endTime",
          "columnType": 4,
          "isNullable": true,
          "dartType": "DateTime?"
        },
        {
          "name": "duration",
          "columnType": 6,
          "isNullable": true,
          "dartType": "Duration?"
        },
        {
          "name": "_servicesMeetingsServicesId",
          "columnType": 2,
          "isNullable": true,
          "dartType": "int?"
        }
      ],
      "foreignKeys": [
        {
          "constraintName": "meetings_fk_0",
          "columns": [
            "_servicesMeetingsServicesId"
          ],
          "referenceTable": "services",
          "referenceTableSchema": "public",
          "referenceColumns": [
            "id"
          ],
          "onUpdate": 3,
          "onDelete": 3
        }
      ],
      "indexes": [
        {
          "indexName": "meetings_pkey",
          "elements": [
            {
              "type": 0,
              "definition": "id"
            }
          ],
          "type": "btree",
          "isUnique": true,
          "isPrimary": true
        }
      ],
      "managed": true
    },
    {
      "name": "members",
      "dartName": "Member",
      "module": "churchapp",
      "schema": "public",
      "columns": [
        {
          "name": "id",
          "columnType": 2,
          "isNullable": false,
          "columnDefault": "nextval('members_id_seq'::regclass)",
          "dartType": "int?"
        },
        {
          "name": "contactId",
          "columnType": 2,
          "isNullable": false,
          "dartType": "int"
        },
        {
          "name": "joiningDate",
          "columnType": 4,
          "isNullable": true,
          "dartType": "DateTime?"
        },
        {
          "name": "occupation",
          "columnType": 0,
          "isNullable": true,
          "dartType": "String?"
        },
        {
          "name": "eduQualification",
          "columnType": 0,
          "isNullable": true,
          "dartType": "String?"
        },
        {
          "name": "language",
          "columnType": 0,
          "isNullable": true,
          "dartType": "String?"
        },
        {
          "name": "race",
          "columnType": 0,
          "isNullable": true,
          "dartType": "String?"
        },
        {
          "name": "ethinicty",
          "columnType": 0,
          "isNullable": true,
          "dartType": "String?"
        },
        {
          "name": "skills",
          "columnType": 8,
          "isNullable": false,
          "dartType": "List<protocol:Skill?>"
        },
        {
          "name": "baptistDate",
          "columnType": 4,
          "isNullable": true,
          "dartType": "DateTime?"
        },
        {
          "name": "membershipFee",
          "columnType": 2,
          "isNullable": true,
          "dartType": "int?"
        },
        {
          "name": "familyId",
          "columnType": 2,
          "isNullable": false,
          "dartType": "int"
        },
        {
          "name": "_familiesMembersFamiliesId",
          "columnType": 2,
          "isNullable": true,
          "dartType": "int?"
        }
      ],
      "foreignKeys": [
        {
          "constraintName": "members_fk_0",
          "columns": [
            "contactId"
          ],
          "referenceTable": "contacts",
          "referenceTableSchema": "public",
          "referenceColumns": [
            "id"
          ],
          "onUpdate": 3,
          "onDelete": 3
        },
        {
          "constraintName": "members_fk_1",
          "columns": [
            "familyId"
          ],
          "referenceTable": "families",
          "referenceTableSchema": "public",
          "referenceColumns": [
            "id"
          ],
          "onUpdate": 3,
          "onDelete": 3
        },
        {
          "constraintName": "members_fk_2",
          "columns": [
            "_familiesMembersFamiliesId"
          ],
          "referenceTable": "families",
          "referenceTableSchema": "public",
          "referenceColumns": [
            "id"
          ],
          "onUpdate": 3,
          "onDelete": 3
        }
      ],
      "indexes": [
        {
          "indexName": "members_pkey",
          "elements": [
            {
              "type": 0,
              "definition": "id"
            }
          ],
          "type": "btree",
          "isUnique": true,
          "isPrimary": true
        }
      ],
      "managed": true
    },
    {
      "name": "positions",
      "dartName": "Position",
      "module": "churchapp",
      "schema": "public",
      "columns": [
        {
          "name": "id",
          "columnType": 2,
          "isNullable": false,
          "columnDefault": "nextval('positions_id_seq'::regclass)",
          "dartType": "int?"
        },
        {
          "name": "description",
          "columnType": 0,
          "isNullable": true,
          "dartType": "String?"
        },
        {
          "name": "color",
          "columnType": 0,
          "isNullable": true,
          "dartType": "String?"
        }
      ],
      "foreignKeys": [],
      "indexes": [
        {
          "indexName": "positions_pkey",
          "elements": [
            {
              "type": 0,
              "definition": "id"
            }
          ],
          "type": "btree",
          "isUnique": true,
          "isPrimary": true
        }
      ],
      "managed": true
    },
    {
      "name": "resource_bookings",
      "dartName": "ResourceBooking",
      "module": "churchapp",
      "schema": "public",
      "columns": [
        {
          "name": "id",
          "columnType": 2,
          "isNullable": false,
          "columnDefault": "nextval('resource_bookings_id_seq'::regclass)",
          "dartType": "int?"
        },
        {
          "name": "createdDateTime",
          "columnType": 4,
          "isNullable": true,
          "dartType": "DateTime?"
        },
        {
          "name": "requestedById",
          "columnType": 2,
          "isNullable": false,
          "dartType": "int"
        },
        {
          "name": "quanity",
          "columnType": 2,
          "isNullable": true,
          "dartType": "int?"
        },
        {
          "name": "duration",
          "columnType": 6,
          "isNullable": true,
          "dartType": "Duration?"
        },
        {
          "name": "startDateTime",
          "columnType": 4,
          "isNullable": true,
          "dartType": "DateTime?"
        },
        {
          "name": "endDateTime",
          "columnType": 4,
          "isNullable": true,
          "dartType": "DateTime?"
        },
        {
          "name": "rate",
          "columnType": 2,
          "isNullable": true,
          "dartType": "int?"
        },
        {
          "name": "amount",
          "columnType": 2,
          "isNullable": true,
          "dartType": "int?"
        },
        {
          "name": "approvalStatus",
          "columnType": 1,
          "isNullable": true,
          "dartType": "bool?"
        },
        {
          "name": "paymentStatus",
          "columnType": 1,
          "isNullable": true,
          "dartType": "bool?"
        },
        {
          "name": "transactionID",
          "columnType": 0,
          "isNullable": true,
          "dartType": "String?"
        },
        {
          "name": "rbookingID",
          "columnType": 2,
          "isNullable": true,
          "dartType": "int?"
        },
        {
          "name": "venueId",
          "columnType": 2,
          "isNullable": false,
          "dartType": "int"
        }
      ],
      "foreignKeys": [
        {
          "constraintName": "resource_bookings_fk_0",
          "columns": [
            "requestedById"
          ],
          "referenceTable": "contacts",
          "referenceTableSchema": "public",
          "referenceColumns": [
            "id"
          ],
          "onUpdate": 3,
          "onDelete": 3
        },
        {
          "constraintName": "resource_bookings_fk_1",
          "columns": [
            "venueId"
          ],
          "referenceTable": "venues",
          "referenceTableSchema": "public",
          "referenceColumns": [
            "id"
          ],
          "onUpdate": 3,
          "onDelete": 3
        }
      ],
      "indexes": [
        {
          "indexName": "resource_bookings_pkey",
          "elements": [
            {
              "type": 0,
              "definition": "id"
            }
          ],
          "type": "btree",
          "isUnique": true,
          "isPrimary": true
        }
      ],
      "managed": true
    },
    {
      "name": "resource_type",
      "dartName": "ResourceType",
      "module": "churchapp",
      "schema": "public",
      "columns": [
        {
          "name": "id",
          "columnType": 2,
          "isNullable": false,
          "columnDefault": "nextval('resource_type_id_seq'::regclass)",
          "dartType": "int?"
        },
        {
          "name": "description",
          "columnType": 0,
          "isNullable": true,
          "dartType": "String?"
        },
        {
          "name": "color",
          "columnType": 0,
          "isNullable": true,
          "dartType": "String?"
        }
      ],
      "foreignKeys": [],
      "indexes": [
        {
          "indexName": "resource_type_pkey",
          "elements": [
            {
              "type": 0,
              "definition": "id"
            }
          ],
          "type": "btree",
          "isUnique": true,
          "isPrimary": true
        }
      ],
      "managed": true
    },
    {
      "name": "resources",
      "dartName": "Resource",
      "module": "churchapp",
      "schema": "public",
      "columns": [
        {
          "name": "id",
          "columnType": 2,
          "isNullable": false,
          "columnDefault": "nextval('resources_id_seq'::regclass)",
          "dartType": "int?"
        },
        {
          "name": "name",
          "columnType": 0,
          "isNullable": true,
          "dartType": "String?"
        },
        {
          "name": "resourceType",
          "columnType": 8,
          "isNullable": true,
          "dartType": "protocol:ResourceType?"
        },
        {
          "name": "location",
          "columnType": 0,
          "isNullable": true,
          "dartType": "String?"
        },
        {
          "name": "quanity",
          "columnType": 2,
          "isNullable": true,
          "dartType": "int?"
        },
        {
          "name": "rent",
          "columnType": 2,
          "isNullable": true,
          "dartType": "int?"
        }
      ],
      "foreignKeys": [],
      "indexes": [
        {
          "indexName": "resources_pkey",
          "elements": [
            {
              "type": 0,
              "definition": "id"
            }
          ],
          "type": "btree",
          "isUnique": true,
          "isPrimary": true
        }
      ],
      "managed": true
    },
    {
      "name": "schedules",
      "dartName": "Schedule",
      "module": "churchapp",
      "schema": "public",
      "columns": [
        {
          "name": "id",
          "columnType": 2,
          "isNullable": false,
          "columnDefault": "nextval('schedules_id_seq'::regclass)",
          "dartType": "int?"
        },
        {
          "name": "title",
          "columnType": 0,
          "isNullable": true,
          "dartType": "String?"
        },
        {
          "name": "description",
          "columnType": 0,
          "isNullable": true,
          "dartType": "String?"
        },
        {
          "name": "createdAt",
          "columnType": 4,
          "isNullable": true,
          "dartType": "DateTime?"
        },
        {
          "name": "createdBy",
          "columnType": 4,
          "isNullable": true,
          "dartType": "DateTime?"
        },
        {
          "name": "dueDateTime",
          "columnType": 4,
          "isNullable": true,
          "dartType": "DateTime?"
        },
        {
          "name": "startDateTime",
          "columnType": 4,
          "isNullable": true,
          "dartType": "DateTime?"
        },
        {
          "name": "endDateTime",
          "columnType": 4,
          "isNullable": true,
          "dartType": "DateTime?"
        },
        {
          "name": "duration",
          "columnType": 6,
          "isNullable": true,
          "dartType": "Duration?"
        },
        {
          "name": "recurring",
          "columnType": 1,
          "isNullable": true,
          "dartType": "bool?"
        },
        {
          "name": "tillDateTime",
          "columnType": 4,
          "isNullable": true,
          "dartType": "DateTime?"
        },
        {
          "name": "interval",
          "columnType": 6,
          "isNullable": true,
          "dartType": "Duration?"
        },
        {
          "name": "totalCount",
          "columnType": 2,
          "isNullable": true,
          "dartType": "int?"
        },
        {
          "name": "status",
          "columnType": 0,
          "isNullable": false,
          "dartType": "protocol:ScheduleStatus"
        },
        {
          "name": "snoozedTo",
          "columnType": 4,
          "isNullable": true,
          "dartType": "DateTime?"
        },
        {
          "name": "snoozeCount",
          "columnType": 2,
          "isNullable": true,
          "dartType": "int?"
        },
        {
          "name": "stoppedBy",
          "columnType": 8,
          "isNullable": true,
          "dartType": "protocol:Contact?"
        }
      ],
      "foreignKeys": [],
      "indexes": [
        {
          "indexName": "schedules_pkey",
          "elements": [
            {
              "type": 0,
              "definition": "id"
            }
          ],
          "type": "btree",
          "isUnique": true,
          "isPrimary": true
        }
      ],
      "managed": true
    },
    {
      "name": "sermon_type",
      "dartName": "SermonType",
      "module": "churchapp",
      "schema": "public",
      "columns": [
        {
          "name": "id",
          "columnType": 2,
          "isNullable": false,
          "columnDefault": "nextval('sermon_type_id_seq'::regclass)",
          "dartType": "int?"
        },
        {
          "name": "description",
          "columnType": 0,
          "isNullable": true,
          "dartType": "String?"
        },
        {
          "name": "color",
          "columnType": 0,
          "isNullable": true,
          "dartType": "String?"
        }
      ],
      "foreignKeys": [],
      "indexes": [
        {
          "indexName": "sermon_type_pkey",
          "elements": [
            {
              "type": 0,
              "definition": "id"
            }
          ],
          "type": "btree",
          "isUnique": true,
          "isPrimary": true
        }
      ],
      "managed": true
    },
    {
      "name": "sermons",
      "dartName": "Sermon",
      "module": "churchapp",
      "schema": "public",
      "columns": [
        {
          "name": "id",
          "columnType": 2,
          "isNullable": false,
          "columnDefault": "nextval('sermons_id_seq'::regclass)",
          "dartType": "int?"
        },
        {
          "name": "title",
          "columnType": 0,
          "isNullable": true,
          "dartType": "String?"
        },
        {
          "name": "subTitle",
          "columnType": 0,
          "isNullable": true,
          "dartType": "String?"
        },
        {
          "name": "addedBy",
          "columnType": 8,
          "isNullable": true,
          "dartType": "protocol:Contact?"
        },
        {
          "name": "published",
          "columnType": 1,
          "isNullable": true,
          "dartType": "bool?"
        },
        {
          "name": "file",
          "columnType": 8,
          "isNullable": true,
          "dartType": "protocol:FileStore?"
        }
      ],
      "foreignKeys": [],
      "indexes": [
        {
          "indexName": "sermons_pkey",
          "elements": [
            {
              "type": 0,
              "definition": "id"
            }
          ],
          "type": "btree",
          "isUnique": true,
          "isPrimary": true
        }
      ],
      "managed": true
    },
    {
      "name": "service_rosters",
      "dartName": "ServiceRoster",
      "module": "churchapp",
      "schema": "public",
      "columns": [
        {
          "name": "id",
          "columnType": 2,
          "isNullable": false,
          "columnDefault": "nextval('service_rosters_id_seq'::regclass)",
          "dartType": "int?"
        },
        {
          "name": "member",
          "columnType": 8,
          "isNullable": false,
          "dartType": "protocol:Contact"
        },
        {
          "name": "service",
          "columnType": 8,
          "isNullable": false,
          "dartType": "protocol:Service"
        },
        {
          "name": "position",
          "columnType": 8,
          "isNullable": false,
          "dartType": "protocol:Position"
        },
        {
          "name": "availability",
          "columnType": 2,
          "isNullable": false,
          "dartType": "int"
        },
        {
          "name": "_servicesRostersServicesId",
          "columnType": 2,
          "isNullable": true,
          "dartType": "int?"
        }
      ],
      "foreignKeys": [
        {
          "constraintName": "service_rosters_fk_0",
          "columns": [
            "_servicesRostersServicesId"
          ],
          "referenceTable": "services",
          "referenceTableSchema": "public",
          "referenceColumns": [
            "id"
          ],
          "onUpdate": 3,
          "onDelete": 3
        }
      ],
      "indexes": [
        {
          "indexName": "service_rosters_pkey",
          "elements": [
            {
              "type": 0,
              "definition": "id"
            }
          ],
          "type": "btree",
          "isUnique": true,
          "isPrimary": true
        }
      ],
      "managed": true
    },
    {
      "name": "service_type",
      "dartName": "ServiceType",
      "module": "churchapp",
      "schema": "public",
      "columns": [
        {
          "name": "id",
          "columnType": 2,
          "isNullable": false,
          "columnDefault": "nextval('service_type_id_seq'::regclass)",
          "dartType": "int?"
        },
        {
          "name": "description",
          "columnType": 0,
          "isNullable": true,
          "dartType": "String?"
        },
        {
          "name": "color",
          "columnType": 0,
          "isNullable": true,
          "dartType": "String?"
        }
      ],
      "foreignKeys": [],
      "indexes": [
        {
          "indexName": "service_type_pkey",
          "elements": [
            {
              "type": 0,
              "definition": "id"
            }
          ],
          "type": "btree",
          "isUnique": true,
          "isPrimary": true
        }
      ],
      "managed": true
    },
    {
      "name": "services",
      "dartName": "Service",
      "module": "churchapp",
      "schema": "public",
      "columns": [
        {
          "name": "id",
          "columnType": 2,
          "isNullable": false,
          "columnDefault": "nextval('services_id_seq'::regclass)",
          "dartType": "int?"
        },
        {
          "name": "title",
          "columnType": 0,
          "isNullable": true,
          "dartType": "String?"
        },
        {
          "name": "description",
          "columnType": 0,
          "isNullable": true,
          "dartType": "String?"
        },
        {
          "name": "type",
          "columnType": 8,
          "isNullable": true,
          "dartType": "protocol:ServiceType?"
        },
        {
          "name": "image",
          "columnType": 5,
          "isNullable": true,
          "dartType": "dart:typed_data:ByteData?"
        },
        {
          "name": "createdAt",
          "columnType": 4,
          "isNullable": true,
          "dartType": "DateTime?"
        },
        {
          "name": "createdBy",
          "columnType": 8,
          "isNullable": true,
          "dartType": "protocol:Contact?"
        }
      ],
      "foreignKeys": [],
      "indexes": [
        {
          "indexName": "services_pkey",
          "elements": [
            {
              "type": 0,
              "definition": "id"
            }
          ],
          "type": "btree",
          "isUnique": true,
          "isPrimary": true
        }
      ],
      "managed": true
    },
    {
      "name": "skill",
      "dartName": "Skill",
      "module": "churchapp",
      "schema": "public",
      "columns": [
        {
          "name": "id",
          "columnType": 2,
          "isNullable": false,
          "columnDefault": "nextval('skill_id_seq'::regclass)",
          "dartType": "int?"
        },
        {
          "name": "description",
          "columnType": 0,
          "isNullable": true,
          "dartType": "String?"
        },
        {
          "name": "color",
          "columnType": 0,
          "isNullable": true,
          "dartType": "String?"
        },
        {
          "name": "createdAt",
          "columnType": 4,
          "isNullable": true,
          "dartType": "DateTime?"
        }
      ],
      "foreignKeys": [],
      "indexes": [
        {
          "indexName": "skill_pkey",
          "elements": [
            {
              "type": 0,
              "definition": "id"
            }
          ],
          "type": "btree",
          "isUnique": true,
          "isPrimary": true
        }
      ],
      "managed": true
    },
    {
      "name": "small_group_members",
      "dartName": "SmallGroupMember",
      "module": "churchapp",
      "schema": "public",
      "columns": [
        {
          "name": "id",
          "columnType": 2,
          "isNullable": false,
          "columnDefault": "nextval('small_group_members_id_seq'::regclass)",
          "dartType": "int?"
        },
        {
          "name": "groupId",
          "columnType": 2,
          "isNullable": false,
          "dartType": "int"
        },
        {
          "name": "memberId",
          "columnType": 2,
          "isNullable": false,
          "dartType": "int"
        },
        {
          "name": "position",
          "columnType": 8,
          "isNullable": false,
          "dartType": "protocol:Position"
        },
        {
          "name": "availablePositonCount",
          "columnType": 2,
          "isNullable": false,
          "dartType": "int"
        }
      ],
      "foreignKeys": [
        {
          "constraintName": "small_group_members_fk_0",
          "columns": [
            "groupId"
          ],
          "referenceTable": "small_groups",
          "referenceTableSchema": "public",
          "referenceColumns": [
            "id"
          ],
          "onUpdate": 3,
          "onDelete": 3
        },
        {
          "constraintName": "small_group_members_fk_1",
          "columns": [
            "memberId"
          ],
          "referenceTable": "contacts",
          "referenceTableSchema": "public",
          "referenceColumns": [
            "id"
          ],
          "onUpdate": 3,
          "onDelete": 3
        }
      ],
      "indexes": [
        {
          "indexName": "small_group_members_pkey",
          "elements": [
            {
              "type": 0,
              "definition": "id"
            }
          ],
          "type": "btree",
          "isUnique": true,
          "isPrimary": true
        }
      ],
      "managed": true
    },
    {
      "name": "small_groups",
      "dartName": "SmallGroup",
      "module": "churchapp",
      "schema": "public",
      "columns": [
        {
          "name": "id",
          "columnType": 2,
          "isNullable": false,
          "columnDefault": "nextval('small_groups_id_seq'::regclass)",
          "dartType": "int?"
        },
        {
          "name": "name",
          "columnType": 0,
          "isNullable": true,
          "dartType": "String?"
        },
        {
          "name": "description",
          "columnType": 0,
          "isNullable": true,
          "dartType": "String?"
        },
        {
          "name": "detail",
          "columnType": 0,
          "isNullable": true,
          "dartType": "String?"
        },
        {
          "name": "type",
          "columnType": 8,
          "isNullable": true,
          "dartType": "protocol:GroupType?"
        }
      ],
      "foreignKeys": [],
      "indexes": [
        {
          "indexName": "small_groups_pkey",
          "elements": [
            {
              "type": 0,
              "definition": "id"
            }
          ],
          "type": "btree",
          "isUnique": true,
          "isPrimary": true
        }
      ],
      "managed": true
    },
    {
      "name": "venue_bookings",
      "dartName": "VenueBooking",
      "module": "churchapp",
      "schema": "public",
      "columns": [
        {
          "name": "id",
          "columnType": 2,
          "isNullable": false,
          "columnDefault": "nextval('venue_bookings_id_seq'::regclass)",
          "dartType": "int?"
        },
        {
          "name": "createdDateTime",
          "columnType": 4,
          "isNullable": true,
          "dartType": "DateTime?"
        },
        {
          "name": "requestedById",
          "columnType": 2,
          "isNullable": false,
          "dartType": "int"
        },
        {
          "name": "duration",
          "columnType": 6,
          "isNullable": true,
          "dartType": "Duration?"
        },
        {
          "name": "startDateTime",
          "columnType": 4,
          "isNullable": true,
          "dartType": "DateTime?"
        },
        {
          "name": "endDateTime",
          "columnType": 4,
          "isNullable": true,
          "dartType": "DateTime?"
        },
        {
          "name": "rate",
          "columnType": 2,
          "isNullable": true,
          "dartType": "int?"
        },
        {
          "name": "amount",
          "columnType": 2,
          "isNullable": true,
          "dartType": "int?"
        },
        {
          "name": "approvalStatus",
          "columnType": 1,
          "isNullable": true,
          "dartType": "bool?"
        },
        {
          "name": "paymentStatus",
          "columnType": 1,
          "isNullable": true,
          "dartType": "bool?"
        },
        {
          "name": "transactionID",
          "columnType": 0,
          "isNullable": true,
          "dartType": "String?"
        },
        {
          "name": "vbookingID",
          "columnType": 2,
          "isNullable": true,
          "dartType": "int?"
        },
        {
          "name": "venueId",
          "columnType": 2,
          "isNullable": false,
          "dartType": "int"
        },
        {
          "name": "resources",
          "columnType": 8,
          "isNullable": true,
          "dartType": "List<protocol:ResourceBooking?>?"
        }
      ],
      "foreignKeys": [
        {
          "constraintName": "venue_bookings_fk_0",
          "columns": [
            "requestedById"
          ],
          "referenceTable": "contacts",
          "referenceTableSchema": "public",
          "referenceColumns": [
            "id"
          ],
          "onUpdate": 3,
          "onDelete": 3
        },
        {
          "constraintName": "venue_bookings_fk_1",
          "columns": [
            "venueId"
          ],
          "referenceTable": "venues",
          "referenceTableSchema": "public",
          "referenceColumns": [
            "id"
          ],
          "onUpdate": 3,
          "onDelete": 3
        }
      ],
      "indexes": [
        {
          "indexName": "venue_bookings_pkey",
          "elements": [
            {
              "type": 0,
              "definition": "id"
            }
          ],
          "type": "btree",
          "isUnique": true,
          "isPrimary": true
        }
      ],
      "managed": true
    },
    {
      "name": "venue_type",
      "dartName": "VenueType",
      "module": "churchapp",
      "schema": "public",
      "columns": [
        {
          "name": "id",
          "columnType": 2,
          "isNullable": false,
          "columnDefault": "nextval('venue_type_id_seq'::regclass)",
          "dartType": "int?"
        },
        {
          "name": "description",
          "columnType": 0,
          "isNullable": true,
          "dartType": "String?"
        },
        {
          "name": "color",
          "columnType": 0,
          "isNullable": true,
          "dartType": "String?"
        }
      ],
      "foreignKeys": [],
      "indexes": [
        {
          "indexName": "venue_type_pkey",
          "elements": [
            {
              "type": 0,
              "definition": "id"
            }
          ],
          "type": "btree",
          "isUnique": true,
          "isPrimary": true
        }
      ],
      "managed": true
    },
    {
      "name": "venues",
      "dartName": "Venue",
      "module": "churchapp",
      "schema": "public",
      "columns": [
        {
          "name": "id",
          "columnType": 2,
          "isNullable": false,
          "columnDefault": "nextval('venues_id_seq'::regclass)",
          "dartType": "int?"
        },
        {
          "name": "name",
          "columnType": 0,
          "isNullable": true,
          "dartType": "String?"
        },
        {
          "name": "venueType",
          "columnType": 8,
          "isNullable": true,
          "dartType": "protocol:VenueType?"
        },
        {
          "name": "location",
          "columnType": 0,
          "isNullable": true,
          "dartType": "String?"
        },
        {
          "name": "capacity",
          "columnType": 2,
          "isNullable": true,
          "dartType": "int?"
        },
        {
          "name": "rent",
          "columnType": 2,
          "isNullable": true,
          "dartType": "int?"
        }
      ],
      "foreignKeys": [],
      "indexes": [
        {
          "indexName": "venues_pkey",
          "elements": [
            {
              "type": 0,
              "definition": "id"
            }
          ],
          "type": "btree",
          "isUnique": true,
          "isPrimary": true
        }
      ],
      "managed": true
    },
    {
      "name": "serverpod_auth_key",
      "dartName": "AuthKey",
      "module": "serverpod",
      "schema": "public",
      "columns": [
        {
          "name": "id",
          "columnType": 2,
          "isNullable": false,
          "columnDefault": "nextval('serverpod_auth_key_id_seq'::regclass)",
          "dartType": "int?"
        },
        {
          "name": "userId",
          "columnType": 2,
          "isNullable": false,
          "dartType": "int"
        },
        {
          "name": "hash",
          "columnType": 0,
          "isNullable": false,
          "dartType": "String"
        },
        {
          "name": "scopeNames",
          "columnType": 8,
          "isNullable": false,
          "dartType": "List<String>"
        },
        {
          "name": "method",
          "columnType": 0,
          "isNullable": false,
          "dartType": "String"
        }
      ],
      "foreignKeys": [],
      "indexes": [
        {
          "indexName": "serverpod_auth_key_pkey",
          "elements": [
            {
              "type": 0,
              "definition": "id"
            }
          ],
          "type": "btree",
          "isUnique": true,
          "isPrimary": true
        },
        {
          "indexName": "serverpod_auth_key_userId_idx",
          "elements": [
            {
              "type": 0,
              "definition": "userId"
            }
          ],
          "type": "btree",
          "isUnique": false,
          "isPrimary": false
        }
      ],
      "managed": true
    },
    {
      "name": "serverpod_cloud_storage",
      "dartName": "CloudStorageEntry",
      "module": "serverpod",
      "schema": "public",
      "columns": [
        {
          "name": "id",
          "columnType": 2,
          "isNullable": false,
          "columnDefault": "nextval('serverpod_cloud_storage_id_seq'::regclass)",
          "dartType": "int?"
        },
        {
          "name": "storageId",
          "columnType": 0,
          "isNullable": false,
          "dartType": "String"
        },
        {
          "name": "path",
          "columnType": 0,
          "isNullable": false,
          "dartType": "String"
        },
        {
          "name": "addedTime",
          "columnType": 4,
          "isNullable": false,
          "dartType": "DateTime"
        },
        {
          "name": "expiration",
          "columnType": 4,
          "isNullable": true,
          "dartType": "DateTime?"
        },
        {
          "name": "byteData",
          "columnType": 5,
          "isNullable": false,
          "dartType": "dart:typed_data:ByteData"
        },
        {
          "name": "verified",
          "columnType": 1,
          "isNullable": false,
          "dartType": "bool"
        }
      ],
      "foreignKeys": [],
      "indexes": [
        {
          "indexName": "serverpod_cloud_storage_pkey",
          "elements": [
            {
              "type": 0,
              "definition": "id"
            }
          ],
          "type": "btree",
          "isUnique": true,
          "isPrimary": true
        },
        {
          "indexName": "serverpod_cloud_storage_path_idx",
          "elements": [
            {
              "type": 0,
              "definition": "storageId"
            },
            {
              "type": 0,
              "definition": "path"
            }
          ],
          "type": "btree",
          "isUnique": true,
          "isPrimary": false
        },
        {
          "indexName": "serverpod_cloud_storage_expiration",
          "elements": [
            {
              "type": 0,
              "definition": "expiration"
            }
          ],
          "type": "btree",
          "isUnique": false,
          "isPrimary": false
        }
      ],
      "managed": true
    },
    {
      "name": "serverpod_cloud_storage_direct_upload",
      "dartName": "CloudStorageDirectUploadEntry",
      "module": "serverpod",
      "schema": "public",
      "columns": [
        {
          "name": "id",
          "columnType": 2,
          "isNullable": false,
          "columnDefault": "nextval('serverpod_cloud_storage_direct_upload_id_seq'::regclass)",
          "dartType": "int?"
        },
        {
          "name": "storageId",
          "columnType": 0,
          "isNullable": false,
          "dartType": "String"
        },
        {
          "name": "path",
          "columnType": 0,
          "isNullable": false,
          "dartType": "String"
        },
        {
          "name": "expiration",
          "columnType": 4,
          "isNullable": false,
          "dartType": "DateTime"
        },
        {
          "name": "authKey",
          "columnType": 0,
          "isNullable": false,
          "dartType": "String"
        }
      ],
      "foreignKeys": [],
      "indexes": [
        {
          "indexName": "serverpod_cloud_storage_direct_upload_pkey",
          "elements": [
            {
              "type": 0,
              "definition": "id"
            }
          ],
          "type": "btree",
          "isUnique": true,
          "isPrimary": true
        },
        {
          "indexName": "serverpod_cloud_storage_direct_upload_storage_path",
          "elements": [
            {
              "type": 0,
              "definition": "storageId"
            },
            {
              "type": 0,
              "definition": "path"
            }
          ],
          "type": "btree",
          "isUnique": true,
          "isPrimary": false
        }
      ],
      "managed": true
    },
    {
      "name": "serverpod_future_call",
      "dartName": "FutureCallEntry",
      "module": "serverpod",
      "schema": "public",
      "columns": [
        {
          "name": "id",
          "columnType": 2,
          "isNullable": false,
          "columnDefault": "nextval('serverpod_future_call_id_seq'::regclass)",
          "dartType": "int?"
        },
        {
          "name": "name",
          "columnType": 0,
          "isNullable": false,
          "dartType": "String"
        },
        {
          "name": "time",
          "columnType": 4,
          "isNullable": false,
          "dartType": "DateTime"
        },
        {
          "name": "serializedObject",
          "columnType": 0,
          "isNullable": true,
          "dartType": "String?"
        },
        {
          "name": "serverId",
          "columnType": 0,
          "isNullable": false,
          "dartType": "String"
        },
        {
          "name": "identifier",
          "columnType": 0,
          "isNullable": true,
          "dartType": "String?"
        }
      ],
      "foreignKeys": [],
      "indexes": [
        {
          "indexName": "serverpod_future_call_pkey",
          "elements": [
            {
              "type": 0,
              "definition": "id"
            }
          ],
          "type": "btree",
          "isUnique": true,
          "isPrimary": true
        },
        {
          "indexName": "serverpod_future_call_time_idx",
          "elements": [
            {
              "type": 0,
              "definition": "time"
            }
          ],
          "type": "btree",
          "isUnique": false,
          "isPrimary": false
        },
        {
          "indexName": "serverpod_future_call_serverId_idx",
          "elements": [
            {
              "type": 0,
              "definition": "serverId"
            }
          ],
          "type": "btree",
          "isUnique": false,
          "isPrimary": false
        },
        {
          "indexName": "serverpod_future_call_identifier_idx",
          "elements": [
            {
              "type": 0,
              "definition": "identifier"
            }
          ],
          "type": "btree",
          "isUnique": false,
          "isPrimary": false
        }
      ],
      "managed": true
    },
    {
      "name": "serverpod_health_connection_info",
      "dartName": "ServerHealthConnectionInfo",
      "module": "serverpod",
      "schema": "public",
      "columns": [
        {
          "name": "id",
          "columnType": 2,
          "isNullable": false,
          "columnDefault": "nextval('serverpod_health_connection_info_id_seq'::regclass)",
          "dartType": "int?"
        },
        {
          "name": "serverId",
          "columnType": 0,
          "isNullable": false,
          "dartType": "String"
        },
        {
          "name": "timestamp",
          "columnType": 4,
          "isNullable": false,
          "dartType": "DateTime"
        },
        {
          "name": "active",
          "columnType": 2,
          "isNullable": false,
          "dartType": "int"
        },
        {
          "name": "closing",
          "columnType": 2,
          "isNullable": false,
          "dartType": "int"
        },
        {
          "name": "idle",
          "columnType": 2,
          "isNullable": false,
          "dartType": "int"
        },
        {
          "name": "granularity",
          "columnType": 2,
          "isNullable": false,
          "dartType": "int"
        }
      ],
      "foreignKeys": [],
      "indexes": [
        {
          "indexName": "serverpod_health_connection_info_pkey",
          "elements": [
            {
              "type": 0,
              "definition": "id"
            }
          ],
          "type": "btree",
          "isUnique": true,
          "isPrimary": true
        },
        {
          "indexName": "serverpod_health_connection_info_timestamp_idx",
          "elements": [
            {
              "type": 0,
              "definition": "timestamp"
            },
            {
              "type": 0,
              "definition": "serverId"
            },
            {
              "type": 0,
              "definition": "granularity"
            }
          ],
          "type": "btree",
          "isUnique": true,
          "isPrimary": false
        }
      ],
      "managed": true
    },
    {
      "name": "serverpod_health_metric",
      "dartName": "ServerHealthMetric",
      "module": "serverpod",
      "schema": "public",
      "columns": [
        {
          "name": "id",
          "columnType": 2,
          "isNullable": false,
          "columnDefault": "nextval('serverpod_health_metric_id_seq'::regclass)",
          "dartType": "int?"
        },
        {
          "name": "name",
          "columnType": 0,
          "isNullable": false,
          "dartType": "String"
        },
        {
          "name": "serverId",
          "columnType": 0,
          "isNullable": false,
          "dartType": "String"
        },
        {
          "name": "timestamp",
          "columnType": 4,
          "isNullable": false,
          "dartType": "DateTime"
        },
        {
          "name": "isHealthy",
          "columnType": 1,
          "isNullable": false,
          "dartType": "bool"
        },
        {
          "name": "value",
          "columnType": 3,
          "isNullable": false,
          "dartType": "double"
        },
        {
          "name": "granularity",
          "columnType": 2,
          "isNullable": false,
          "dartType": "int"
        }
      ],
      "foreignKeys": [],
      "indexes": [
        {
          "indexName": "serverpod_health_metric_pkey",
          "elements": [
            {
              "type": 0,
              "definition": "id"
            }
          ],
          "type": "btree",
          "isUnique": true,
          "isPrimary": true
        },
        {
          "indexName": "serverpod_health_metric_timestamp_idx",
          "elements": [
            {
              "type": 0,
              "definition": "timestamp"
            },
            {
              "type": 0,
              "definition": "serverId"
            },
            {
              "type": 0,
              "definition": "name"
            },
            {
              "type": 0,
              "definition": "granularity"
            }
          ],
          "type": "btree",
          "isUnique": true,
          "isPrimary": false
        }
      ],
      "managed": true
    },
    {
      "name": "serverpod_log",
      "dartName": "LogEntry",
      "module": "serverpod",
      "schema": "public",
      "columns": [
        {
          "name": "id",
          "columnType": 2,
          "isNullable": false,
          "columnDefault": "nextval('serverpod_log_id_seq'::regclass)",
          "dartType": "int?"
        },
        {
          "name": "sessionLogId",
          "columnType": 2,
          "isNullable": false,
          "dartType": "int"
        },
        {
          "name": "messageId",
          "columnType": 2,
          "isNullable": true,
          "dartType": "int?"
        },
        {
          "name": "reference",
          "columnType": 0,
          "isNullable": true,
          "dartType": "String?"
        },
        {
          "name": "serverId",
          "columnType": 0,
          "isNullable": false,
          "dartType": "String"
        },
        {
          "name": "time",
          "columnType": 4,
          "isNullable": false,
          "dartType": "DateTime"
        },
        {
          "name": "logLevel",
          "columnType": 2,
          "isNullable": false,
          "dartType": "protocol:LogLevel"
        },
        {
          "name": "message",
          "columnType": 0,
          "isNullable": false,
          "dartType": "String"
        },
        {
          "name": "error",
          "columnType": 0,
          "isNullable": true,
          "dartType": "String?"
        },
        {
          "name": "stackTrace",
          "columnType": 0,
          "isNullable": true,
          "dartType": "String?"
        },
        {
          "name": "order",
          "columnType": 2,
          "isNullable": false,
          "dartType": "int"
        }
      ],
      "foreignKeys": [
        {
          "constraintName": "serverpod_log_fk_0",
          "columns": [
            "sessionLogId"
          ],
          "referenceTable": "serverpod_session_log",
          "referenceTableSchema": "public",
          "referenceColumns": [
            "id"
          ],
          "onUpdate": 3,
          "onDelete": 4
        }
      ],
      "indexes": [
        {
          "indexName": "serverpod_log_pkey",
          "elements": [
            {
              "type": 0,
              "definition": "id"
            }
          ],
          "type": "btree",
          "isUnique": true,
          "isPrimary": true
        },
        {
          "indexName": "serverpod_log_sessionLogId_idx",
          "elements": [
            {
              "type": 0,
              "definition": "sessionLogId"
            }
          ],
          "type": "btree",
          "isUnique": false,
          "isPrimary": false
        }
      ],
      "managed": true
    },
    {
      "name": "serverpod_message_log",
      "dartName": "MessageLogEntry",
      "module": "serverpod",
      "schema": "public",
      "columns": [
        {
          "name": "id",
          "columnType": 2,
          "isNullable": false,
          "columnDefault": "nextval('serverpod_message_log_id_seq'::regclass)",
          "dartType": "int?"
        },
        {
          "name": "sessionLogId",
          "columnType": 2,
          "isNullable": false,
          "dartType": "int"
        },
        {
          "name": "serverId",
          "columnType": 0,
          "isNullable": false,
          "dartType": "String"
        },
        {
          "name": "messageId",
          "columnType": 2,
          "isNullable": false,
          "dartType": "int"
        },
        {
          "name": "endpoint",
          "columnType": 0,
          "isNullable": false,
          "dartType": "String"
        },
        {
          "name": "messageName",
          "columnType": 0,
          "isNullable": false,
          "dartType": "String"
        },
        {
          "name": "duration",
          "columnType": 3,
          "isNullable": false,
          "dartType": "double"
        },
        {
          "name": "error",
          "columnType": 0,
          "isNullable": true,
          "dartType": "String?"
        },
        {
          "name": "stackTrace",
          "columnType": 0,
          "isNullable": true,
          "dartType": "String?"
        },
        {
          "name": "slow",
          "columnType": 1,
          "isNullable": false,
          "dartType": "bool"
        },
        {
          "name": "order",
          "columnType": 2,
          "isNullable": false,
          "dartType": "int"
        }
      ],
      "foreignKeys": [
        {
          "constraintName": "serverpod_message_log_fk_0",
          "columns": [
            "sessionLogId"
          ],
          "referenceTable": "serverpod_session_log",
          "referenceTableSchema": "public",
          "referenceColumns": [
            "id"
          ],
          "onUpdate": 3,
          "onDelete": 4
        }
      ],
      "indexes": [
        {
          "indexName": "serverpod_message_log_pkey",
          "elements": [
            {
              "type": 0,
              "definition": "id"
            }
          ],
          "type": "btree",
          "isUnique": true,
          "isPrimary": true
        }
      ],
      "managed": true
    },
    {
      "name": "serverpod_method",
      "dartName": "MethodInfo",
      "module": "serverpod",
      "schema": "public",
      "columns": [
        {
          "name": "id",
          "columnType": 2,
          "isNullable": false,
          "columnDefault": "nextval('serverpod_method_id_seq'::regclass)",
          "dartType": "int?"
        },
        {
          "name": "endpoint",
          "columnType": 0,
          "isNullable": false,
          "dartType": "String"
        },
        {
          "name": "method",
          "columnType": 0,
          "isNullable": false,
          "dartType": "String"
        }
      ],
      "foreignKeys": [],
      "indexes": [
        {
          "indexName": "serverpod_method_pkey",
          "elements": [
            {
              "type": 0,
              "definition": "id"
            }
          ],
          "type": "btree",
          "isUnique": true,
          "isPrimary": true
        },
        {
          "indexName": "serverpod_method_endpoint_method_idx",
          "elements": [
            {
              "type": 0,
              "definition": "endpoint"
            },
            {
              "type": 0,
              "definition": "method"
            }
          ],
          "type": "btree",
          "isUnique": true,
          "isPrimary": false
        }
      ],
      "managed": true
    },
    {
      "name": "serverpod_migrations",
      "dartName": "DatabaseMigrationVersion",
      "module": "serverpod",
      "schema": "public",
      "columns": [
        {
          "name": "id",
          "columnType": 2,
          "isNullable": false,
          "columnDefault": "nextval('serverpod_migrations_id_seq'::regclass)",
          "dartType": "int?"
        },
        {
          "name": "module",
          "columnType": 0,
          "isNullable": false,
          "dartType": "String"
        },
        {
          "name": "version",
          "columnType": 0,
          "isNullable": false,
          "dartType": "String"
        },
        {
          "name": "timestamp",
          "columnType": 4,
          "isNullable": true,
          "dartType": "DateTime?"
        }
      ],
      "foreignKeys": [],
      "indexes": [
        {
          "indexName": "serverpod_migrations_pkey",
          "elements": [
            {
              "type": 0,
              "definition": "id"
            }
          ],
          "type": "btree",
          "isUnique": true,
          "isPrimary": true
        },
        {
          "indexName": "serverpod_migrations_ids",
          "elements": [
            {
              "type": 0,
              "definition": "module"
            }
          ],
          "type": "btree",
          "isUnique": true,
          "isPrimary": false
        }
      ],
      "managed": true
    },
    {
      "name": "serverpod_query_log",
      "dartName": "QueryLogEntry",
      "module": "serverpod",
      "schema": "public",
      "columns": [
        {
          "name": "id",
          "columnType": 2,
          "isNullable": false,
          "columnDefault": "nextval('serverpod_query_log_id_seq'::regclass)",
          "dartType": "int?"
        },
        {
          "name": "serverId",
          "columnType": 0,
          "isNullable": false,
          "dartType": "String"
        },
        {
          "name": "sessionLogId",
          "columnType": 2,
          "isNullable": false,
          "dartType": "int"
        },
        {
          "name": "messageId",
          "columnType": 2,
          "isNullable": true,
          "dartType": "int?"
        },
        {
          "name": "query",
          "columnType": 0,
          "isNullable": false,
          "dartType": "String"
        },
        {
          "name": "duration",
          "columnType": 3,
          "isNullable": false,
          "dartType": "double"
        },
        {
          "name": "numRows",
          "columnType": 2,
          "isNullable": true,
          "dartType": "int?"
        },
        {
          "name": "error",
          "columnType": 0,
          "isNullable": true,
          "dartType": "String?"
        },
        {
          "name": "stackTrace",
          "columnType": 0,
          "isNullable": true,
          "dartType": "String?"
        },
        {
          "name": "slow",
          "columnType": 1,
          "isNullable": false,
          "dartType": "bool"
        },
        {
          "name": "order",
          "columnType": 2,
          "isNullable": false,
          "dartType": "int"
        }
      ],
      "foreignKeys": [
        {
          "constraintName": "serverpod_query_log_fk_0",
          "columns": [
            "sessionLogId"
          ],
          "referenceTable": "serverpod_session_log",
          "referenceTableSchema": "public",
          "referenceColumns": [
            "id"
          ],
          "onUpdate": 3,
          "onDelete": 4
        }
      ],
      "indexes": [
        {
          "indexName": "serverpod_query_log_pkey",
          "elements": [
            {
              "type": 0,
              "definition": "id"
            }
          ],
          "type": "btree",
          "isUnique": true,
          "isPrimary": true
        },
        {
          "indexName": "serverpod_query_log_sessionLogId_idx",
          "elements": [
            {
              "type": 0,
              "definition": "sessionLogId"
            }
          ],
          "type": "btree",
          "isUnique": false,
          "isPrimary": false
        }
      ],
      "managed": true
    },
    {
      "name": "serverpod_readwrite_test",
      "dartName": "ReadWriteTestEntry",
      "module": "serverpod",
      "schema": "public",
      "columns": [
        {
          "name": "id",
          "columnType": 2,
          "isNullable": false,
          "columnDefault": "nextval('serverpod_readwrite_test_id_seq'::regclass)",
          "dartType": "int?"
        },
        {
          "name": "number",
          "columnType": 2,
          "isNullable": false,
          "dartType": "int"
        }
      ],
      "foreignKeys": [],
      "indexes": [
        {
          "indexName": "serverpod_readwrite_test_pkey",
          "elements": [
            {
              "type": 0,
              "definition": "id"
            }
          ],
          "type": "btree",
          "isUnique": true,
          "isPrimary": true
        }
      ],
      "managed": true
    },
    {
      "name": "serverpod_runtime_settings",
      "dartName": "RuntimeSettings",
      "module": "serverpod",
      "schema": "public",
      "columns": [
        {
          "name": "id",
          "columnType": 2,
          "isNullable": false,
          "columnDefault": "nextval('serverpod_runtime_settings_id_seq'::regclass)",
          "dartType": "int?"
        },
        {
          "name": "logSettings",
          "columnType": 8,
          "isNullable": false,
          "dartType": "protocol:LogSettings"
        },
        {
          "name": "logSettingsOverrides",
          "columnType": 8,
          "isNullable": false,
          "dartType": "List<protocol:LogSettingsOverride>"
        },
        {
          "name": "logServiceCalls",
          "columnType": 1,
          "isNullable": false,
          "dartType": "bool"
        },
        {
          "name": "logMalformedCalls",
          "columnType": 1,
          "isNullable": false,
          "dartType": "bool"
        }
      ],
      "foreignKeys": [],
      "indexes": [
        {
          "indexName": "serverpod_runtime_settings_pkey",
          "elements": [
            {
              "type": 0,
              "definition": "id"
            }
          ],
          "type": "btree",
          "isUnique": true,
          "isPrimary": true
        }
      ],
      "managed": true
    },
    {
      "name": "serverpod_session_log",
      "dartName": "SessionLogEntry",
      "module": "serverpod",
      "schema": "public",
      "columns": [
        {
          "name": "id",
          "columnType": 2,
          "isNullable": false,
          "columnDefault": "nextval('serverpod_session_log_id_seq'::regclass)",
          "dartType": "int?"
        },
        {
          "name": "serverId",
          "columnType": 0,
          "isNullable": false,
          "dartType": "String"
        },
        {
          "name": "time",
          "columnType": 4,
          "isNullable": false,
          "dartType": "DateTime"
        },
        {
          "name": "module",
          "columnType": 0,
          "isNullable": true,
          "dartType": "String?"
        },
        {
          "name": "endpoint",
          "columnType": 0,
          "isNullable": true,
          "dartType": "String?"
        },
        {
          "name": "method",
          "columnType": 0,
          "isNullable": true,
          "dartType": "String?"
        },
        {
          "name": "duration",
          "columnType": 3,
          "isNullable": true,
          "dartType": "double?"
        },
        {
          "name": "numQueries",
          "columnType": 2,
          "isNullable": true,
          "dartType": "int?"
        },
        {
          "name": "slow",
          "columnType": 1,
          "isNullable": true,
          "dartType": "bool?"
        },
        {
          "name": "error",
          "columnType": 0,
          "isNullable": true,
          "dartType": "String?"
        },
        {
          "name": "stackTrace",
          "columnType": 0,
          "isNullable": true,
          "dartType": "String?"
        },
        {
          "name": "authenticatedUserId",
          "columnType": 2,
          "isNullable": true,
          "dartType": "int?"
        },
        {
          "name": "isOpen",
          "columnType": 1,
          "isNullable": true,
          "dartType": "bool?"
        },
        {
          "name": "touched",
          "columnType": 4,
          "isNullable": false,
          "dartType": "DateTime"
        }
      ],
      "foreignKeys": [],
      "indexes": [
        {
          "indexName": "serverpod_session_log_pkey",
          "elements": [
            {
              "type": 0,
              "definition": "id"
            }
          ],
          "type": "btree",
          "isUnique": true,
          "isPrimary": true
        },
        {
          "indexName": "serverpod_session_log_serverid_idx",
          "elements": [
            {
              "type": 0,
              "definition": "serverId"
            }
          ],
          "type": "btree",
          "isUnique": false,
          "isPrimary": false
        },
        {
          "indexName": "serverpod_session_log_touched_idx",
          "elements": [
            {
              "type": 0,
              "definition": "touched"
            }
          ],
          "type": "btree",
          "isUnique": false,
          "isPrimary": false
        },
        {
          "indexName": "serverpod_session_log_isopen_idx",
          "elements": [
            {
              "type": 0,
              "definition": "isOpen"
            }
          ],
          "type": "btree",
          "isUnique": false,
          "isPrimary": false
        }
      ],
      "managed": true
    }
  ],
  "installedModules": [
    {
      "module": "churchapp",
      "version": "20240319163250170"
    },
    {
      "module": "serverpod",
      "version": "20240115074235544"
    }
  ],
  "migrationApiVersion": 1
}